pytest_fixture_rtttg.py
pytest_fixture_rtttg-0.1.1.dist-info/entry_points.txt
pytest_fixture_rtttg-0.1.1.dist-info/WHEEL
pytest_fixture_rtttg-0.1.1.dist-info/METADATA
pytest_fixture_rtttg-0.1.1.dist-info/RECORD
