Metadata-Version: 2.1
Name: pytest-fixture-rtttg
Version: 0.1.1
Summary: Warn or fail on fixture name clash
Home-page: https://github.com/L3viathan/pytest-fixture-rtttg
License: WTFPL
Author: L3viathan
Author-email: git@l3vi.de
Requires-Python: >=3.7,<4.0
Classifier: License :: Other/Proprietary License
Classifier: Programming Language :: Python :: 3
Classifier: Programming Language :: Python :: 3.10
Classifier: Programming Language :: Python :: 3.7
Classifier: Programming Language :: Python :: 3.8
Classifier: Programming Language :: Python :: 3.9
Requires-Dist: pytest (>=7.0.1,<8.0.0)
Project-URL: Repository, https://github.com/L3viathan/pytest-fixture-rtttg
